LICENSE
MANIFEST.in
README.rst
pyproject.toml
setup.py
django_celery_stack/__init__.py
django_celery_stack/apps.py
django_celery_stack/managers.py
django_celery_stack/tasks.py
django_celery_stack/tests.py
django_celery_stack/urls.py
django_celery_stack/views.py
django_celery_stack.egg-info/PKG-INFO
django_celery_stack.egg-info/SOURCES.txt
django_celery_stack.egg-info/dependency_links.txt
django_celery_stack.egg-info/requires.txt
django_celery_stack.egg-info/top_level.txt
django_celery_stack/admin/__init__.py
django_celery_stack/admin/customTaskTesult.py
django_celery_stack/admin/registeredTask.py
django_celery_stack/admin/taskResult.py
django_celery_stack/admin/taskStates.py
django_celery_stack/admin/taskchain.py
django_celery_stack/backends/__init__.py
django_celery_stack/backends/database.py
django_celery_stack/locale/zh_Hans/LC_MESSAGES/django.mo
django_celery_stack/locale/zh_Hans/LC_MESSAGES/django.po
django_celery_stack/migrations/0001_initial.py
django_celery_stack/migrations/__init__.py
django_celery_stack/models/__init__.py