Metadata-Version: 2.1
Name: django-celery-stack
Version: 1.0.2
Summary: A full stack solution for celery and Django compatibility. The merge of django-celery-beat, django-celery-result, django-celery-progress.
Author-email: Sadam·Sadik <Haoke98@outlook.com>
Maintainer-email: Sadam·Sadik <Haoke98@outlook.com>
License: Open Source License (GPL v3)
Project-URL: Homepage, https://github.com/Haoke98/django-celery-stack
Project-URL: Documentation, https://github.com/Haoke98/django-celery-stack/README.md
Project-URL: Repository, https://github.com/Haoke98/django-celery-stack.git
Project-URL: Bug Tracker, https://github.com/Haoke98/django-celery-stack/issues
Project-URL: Changelog, https://github.com/Haoke98/django-celery-stack/releases
Keywords: celery,django,task-scheduler,django-celery-beat,django-celery,django-celery-result,task-distribution,django-celery-progress
Classifier: Development Status :: 5 - Production/Stable
Classifier: Environment :: Console
Classifier: Intended Audience :: Developers
Classifier: Intended Audience :: Information Technology
Classifier: License :: OSI Approved :: Apache Software License
Classifier: Natural Language :: English
Classifier: Operating System :: OS Independent
Classifier: Programming Language :: Python :: 3.11
Classifier: Programming Language :: Python :: 3.10
Classifier: Programming Language :: Python :: 3.9
Classifier: Programming Language :: Python :: 3.8
Classifier: Programming Language :: Python :: 3.7
Classifier: Programming Language :: Python :: 3.6
Classifier: Framework :: Celery
Classifier: Framework :: Django
Classifier: Topic :: Scientific/Engineering :: Interface Engine/Protocol Translator
Requires-Python: >=3.6
License-File: LICENSE
